{"__type__":"sp.SkeletonData","_name":"lw","_skeletonJson":{"skeleton":{"hash":"OeJrfI6a92D/g/egL3oHkpSS00g","spine":"3.8.99","x":-138.39,"y":0.18,"width":243.62,"height":279.35,"images":"./images/","audio":"C:/Users/QianHu002/Desktop/动画/登山极限摩托狂飙/礼物按钮/images"},"bones":[{"name":"root"},{"name":"lw_di","parent":"root"},{"name":"lw_zi","parent":"lw_di","x":-3.61,"y":84.28},{"name":"lw_z","parent":"lw_di","rotation":-14.32,"x":45.18,"y":184.42},{"name":"lw_lan","parent":"lw_di","rotation":-11.24,"x":-44.1,"y":192.32},{"name":"lw_gth","parent":"lw_di","x":-102.63,"y":181.69}],"slots":[{"name":"lw_di","bone":"lw_di","attachment":"lw_di"},{"name":"lw_z","bone":"lw_z","attachment":"lw_z"},{"name":"lw_lan","bone":"lw_lan","attachment":"lw_lan"},{"name":"lw_zi","bone":"lw_zi","attachment":"lw_zi"},{"name":"lw_gth","bone":"lw_gth","attachment":"lw_gth"},{"name":"lw_zi2","bone":"lw_zi"}],"skins":[{"name":"default","attachments":{"lw_di":{"lw_di":{"x":-0.39,"y":94.68,"width":210,"height":189}},"lw_gth":{"lw_gth":{"x":3.74,"y":34.49,"width":79,"height":80}},"lw_lan":{"lw_lan":{"width":130,"height":152}},"lw_z":{"lw_z":{"width":90,"height":133}},"lw_zi":{"lw_zi":{"x":3.23,"y":-1.1,"width":134,"height":54},"lw_zi2":{"x":1.89,"y":1.74,"width":98,"height":49}}}}],"animations":{"animation2_en":{"slots":{"lw_gth":{"attachment":[{"name":null}]},"lw_zi":{"attachment":[{"name":"lw_zi2"}]}},"bones":{"lw_z":{"rotate":[{"curve":0.25,"c3":0.75},{"time":0.1667,"angle":-6.54,"curve":0.25,"c3":0.75},{"time":0.3333,"curve":0.25,"c3":0.75},{"time":0.5,"angle":-6.54,"curve":0.25,"c3":0.75},{"time":0.6667,"curve":0.25,"c3":0.75},{"time":0.8333,"angle":-6.54,"curve":"stepped"},{"time":1,"angle":-6.54,"curve":0.25,"c3":0.75},{"time":1.1,"angle":-76.29,"curve":0.25,"c3":0.75},{"time":1.1667,"angle":-165.02,"curve":0.25,"c3":0.75},{"time":1.2667,"angle":105.71,"curve":0.25,"c3":0.75},{"time":1.3333,"angle":-6.54}],"translate":[{"time":0.8333,"curve":0.25,"c3":0.75},{"time":1,"y":69.81,"curve":"stepped"},{"time":1.3333,"y":69.81,"curve":0.25,"c3":0.75},{"time":1.5}]},"lw_lan":{"rotate":[{"curve":0.25,"c3":0.75},{"time":0.1667,"angle":7.15,"curve":"stepped"},{"time":0.3333,"angle":7.15,"curve":0.25,"c3":0.75},{"time":0.4,"angle":-76.85,"curve":0.25,"c3":0.75},{"time":0.5,"angle":-167.81,"curve":0.25,"c3":0.75},{"time":0.5667,"angle":99.71,"curve":0.25,"c3":0.75},{"time":0.6667,"angle":7.15,"curve":"stepped"},{"time":0.8333,"angle":7.15,"curve":0.25,"c3":0.75},{"time":1,"curve":0.25,"c3":0.75},{"time":1.1667,"angle":7.15,"curve":0.25,"c3":0.75},{"time":1.3333,"curve":0.25,"c3":0.75},{"time":1.5,"angle":7.15}],"translate":[{"time":0.1667,"curve":0.25,"c3":0.75},{"time":0.3333,"y":113.27,"curve":"stepped"},{"time":0.6667,"y":113.27,"curve":0.25,"c3":0.75},{"time":0.8333}]}}},"animation2_zh":{"slots":{"lw_gth":{"attachment":[{"name":null}]}},"bones":{"lw_z":{"rotate":[{"curve":0.25,"c3":0.75},{"time":0.1667,"angle":-6.54,"curve":0.25,"c3":0.75},{"time":0.3333,"curve":0.25,"c3":0.75},{"time":0.5,"angle":-6.54,"curve":0.25,"c3":0.75},{"time":0.6667,"curve":0.25,"c3":0.75},{"time":0.8333,"angle":-6.54,"curve":"stepped"},{"time":1,"angle":-6.54,"curve":0.25,"c3":0.75},{"time":1.1,"angle":-76.29,"curve":0.25,"c3":0.75},{"time":1.1667,"angle":-165.02,"curve":0.25,"c3":0.75},{"time":1.2667,"angle":105.71,"curve":0.25,"c3":0.75},{"time":1.3333,"angle":-6.54}],"translate":[{"time":0.8333,"curve":0.25,"c3":0.75},{"time":1,"y":69.81,"curve":"stepped"},{"time":1.3333,"y":69.81,"curve":0.25,"c3":0.75},{"time":1.5}]},"lw_lan":{"rotate":[{"curve":0.25,"c3":0.75},{"time":0.1667,"angle":7.15,"curve":"stepped"},{"time":0.3333,"angle":7.15,"curve":0.25,"c3":0.75},{"time":0.4,"angle":-76.85,"curve":0.25,"c3":0.75},{"time":0.5,"angle":-167.81,"curve":0.25,"c3":0.75},{"time":0.5667,"angle":99.71,"curve":0.25,"c3":0.75},{"time":0.6667,"angle":7.15,"curve":"stepped"},{"time":0.8333,"angle":7.15,"curve":0.25,"c3":0.75},{"time":1,"curve":0.25,"c3":0.75},{"time":1.1667,"angle":7.15,"curve":0.25,"c3":0.75},{"time":1.3333,"curve":0.25,"c3":0.75},{"time":1.5,"angle":7.15}],"translate":[{"time":0.1667,"curve":0.25,"c3":0.75},{"time":0.3333,"y":113.27,"curve":"stepped"},{"time":0.6667,"y":113.27,"curve":0.25,"c3":0.75},{"time":0.8333}]}}},"animation_en":{"slots":{"lw_zi":{"attachment":[{"name":"lw_zi2"}]}},"bones":{"lw_z":{"rotate":[{"curve":0.25,"c3":0.75},{"time":0.1667,"angle":-6.54,"curve":0.25,"c3":0.75},{"time":0.3333,"curve":0.25,"c3":0.75},{"time":0.5,"angle":-6.54,"curve":0.25,"c3":0.75},{"time":0.6667,"curve":0.25,"c3":0.75},{"time":0.8333,"angle":-6.54,"curve":"stepped"},{"time":1,"angle":-6.54,"curve":0.25,"c3":0.75},{"time":1.1,"angle":-76.29,"curve":0.25,"c3":0.75},{"time":1.1667,"angle":-165.02,"curve":0.25,"c3":0.75},{"time":1.2667,"angle":105.71,"curve":0.25,"c3":0.75},{"time":1.3333,"angle":-6.54}],"translate":[{"time":0.8333,"curve":0.25,"c3":0.75},{"time":1,"y":69.81,"curve":"stepped"},{"time":1.3333,"y":69.81,"curve":0.25,"c3":0.75},{"time":1.5}]},"lw_lan":{"rotate":[{"curve":0.25,"c3":0.75},{"time":0.1667,"angle":7.15,"curve":"stepped"},{"time":0.3333,"angle":7.15,"curve":0.25,"c3":0.75},{"time":0.4,"angle":-76.85,"curve":0.25,"c3":0.75},{"time":0.5,"angle":-167.81,"curve":0.25,"c3":0.75},{"time":0.5667,"angle":99.71,"curve":0.25,"c3":0.75},{"time":0.6667,"angle":7.15,"curve":"stepped"},{"time":0.8333,"angle":7.15,"curve":0.25,"c3":0.75},{"time":1,"curve":0.25,"c3":0.75},{"time":1.1667,"angle":7.15,"curve":0.25,"c3":0.75},{"time":1.3333,"curve":0.25,"c3":0.75},{"time":1.5,"angle":7.15}],"translate":[{"time":0.1667,"curve":0.25,"c3":0.75},{"time":0.3333,"y":113.27,"curve":"stepped"},{"time":0.6667,"y":113.27,"curve":0.25,"c3":0.75},{"time":0.8333}]},"lw_gth":{"rotate":[{"curve":0.25,"c3":0.75},{"time":0.3667,"angle":8.49,"curve":0.25,"c3":0.75},{"time":0.7333,"curve":0.25,"c3":0.75},{"time":1.1333,"angle":8.49,"curve":0.25,"c3":0.75},{"time":1.5}],"scale":[{"curve":0.25,"c3":0.75},{"time":0.3667,"x":1.173,"y":1.173,"curve":0.25,"c3":0.75},{"time":0.7333,"curve":0.25,"c3":0.75},{"time":1.1333,"x":1.173,"y":1.173,"curve":0.25,"c3":0.75},{"time":1.5}]}}},"animation_zh":{"bones":{"lw_z":{"rotate":[{"curve":0.25,"c3":0.75},{"time":0.1667,"angle":-6.54,"curve":0.25,"c3":0.75},{"time":0.3333,"curve":0.25,"c3":0.75},{"time":0.5,"angle":-6.54,"curve":0.25,"c3":0.75},{"time":0.6667,"curve":0.25,"c3":0.75},{"time":0.8333,"angle":-6.54,"curve":"stepped"},{"time":1,"angle":-6.54,"curve":0.25,"c3":0.75},{"time":1.1,"angle":-76.29,"curve":0.25,"c3":0.75},{"time":1.1667,"angle":-165.02,"curve":0.25,"c3":0.75},{"time":1.2667,"angle":105.71,"curve":0.25,"c3":0.75},{"time":1.3333,"angle":-6.54}],"translate":[{"time":0.8333,"curve":0.25,"c3":0.75},{"time":1,"y":69.81,"curve":"stepped"},{"time":1.3333,"y":69.81,"curve":0.25,"c3":0.75},{"time":1.5}]},"lw_lan":{"rotate":[{"curve":0.25,"c3":0.75},{"time":0.1667,"angle":7.15,"curve":"stepped"},{"time":0.3333,"angle":7.15,"curve":0.25,"c3":0.75},{"time":0.4,"angle":-76.85,"curve":0.25,"c3":0.75},{"time":0.5,"angle":-167.81,"curve":0.25,"c3":0.75},{"time":0.5667,"angle":99.71,"curve":0.25,"c3":0.75},{"time":0.6667,"angle":7.15,"curve":"stepped"},{"time":0.8333,"angle":7.15,"curve":0.25,"c3":0.75},{"time":1,"curve":0.25,"c3":0.75},{"time":1.1667,"angle":7.15,"curve":0.25,"c3":0.75},{"time":1.3333,"curve":0.25,"c3":0.75},{"time":1.5,"angle":7.15}],"translate":[{"time":0.1667,"curve":0.25,"c3":0.75},{"time":0.3333,"y":113.27,"curve":"stepped"},{"time":0.6667,"y":113.27,"curve":0.25,"c3":0.75},{"time":0.8333}]},"lw_gth":{"rotate":[{"curve":0.25,"c3":0.75},{"time":0.3667,"angle":8.49,"curve":0.25,"c3":0.75},{"time":0.7333,"curve":0.25,"c3":0.75},{"time":1.1333,"angle":8.49,"curve":0.25,"c3":0.75},{"time":1.5}],"scale":[{"curve":0.25,"c3":0.75},{"time":0.3667,"x":1.173,"y":1.173,"curve":0.25,"c3":0.75},{"time":0.7333,"curve":0.25,"c3":0.75},{"time":1.1333,"x":1.173,"y":1.173,"curve":0.25,"c3":0.75},{"time":1.5}]}}}}},"_atlasText":"\r\nlw.png\r\nsize: 512,256\r\nformat: RGBA8888\r\nfilter: Linear,Linear\r\nrepeat: none\r\nlw_di\r\n  rotate: false\r\n  xy: 2, 46\r\n  size: 210, 189\r\n  orig: 210, 189\r\n  offset: 0, 0\r\n  index: -1\r\nlw_gth\r\n  rotate: false\r\n  xy: 350, 22\r\n  size: 78, 78\r\n  orig: 79, 80\r\n  offset: 0, 1\r\n  index: -1\r\nlw_lan\r\n  rotate: true\r\n  xy: 214, 106\r\n  size: 129, 152\r\n  orig: 130, 152\r\n  offset: 1, 0\r\n  index: -1\r\nlw_z\r\n  rotate: false\r\n  xy: 368, 102\r\n  size: 90, 133\r\n  orig: 90, 133\r\n  offset: 0, 0\r\n  index: -1\r\nlw_zi\r\n  rotate: false\r\n  xy: 214, 50\r\n  size: 134, 54\r\n  orig: 134, 54\r\n  offset: 0, 0\r\n  index: -1\r\nlw_zi2\r\n  rotate: true\r\n  xy: 430, 2\r\n  size: 98, 49\r\n  orig: 98, 49\r\n  offset: 0, 0\r\n  index: -1\r\n","textures":[{"__uuid__":"cbBl0/SjxBHa3k8f+eOXAR"}],"textureNames":["lw.png"]}